forensicfit/__init__.py
forensicfit/version.py
forensicfit/core/__init__.py
forensicfit/core/analyzer.py
forensicfit/core/data.py
forensicfit/core/image.py
forensicfit/core/metadata.py
forensicfit/core/tape.py
forensicfit/database/__init__.py
forensicfit/database/database.py
forensicfit/machine_learning/__init__.py
forensicfit/machine_learning/combineDT.py
forensicfit/machine_learning/data_pipeline.py
forensicfit/machine_learning/dataset.py
forensicfit/machine_learning/download.py
forensicfit/machine_learning/download_models.py
forensicfit/machine_learning/evaluate.py
forensicfit/machine_learning/model.py
forensicfit/machine_learning/predict.py
forensicfit/machine_learning/trainer_pytorch.py
forensicfit/machine_learning/trainer_tensorflow.py
forensicfit/machine_learning/data/__init__.py
forensicfit/machine_learning/data/data_generation.py
forensicfit/machine_learning/data/data_ingestion.py
forensicfit/machine_learning/data/data_preprocessing.py
forensicfit/utils/__init__.py
forensicfit/utils/array_tools.py
forensicfit/utils/general.py
forensicfit/utils/image_tools.py
forensicfit/utils/plotter.py
forensicfit-2.0.152.data/scripts/create_metadata.py
forensicfit-2.0.152.data/scripts/preprocess_bin_based.py
forensicfit-2.0.152.data/scripts/store_on_db.py
forensicfit-2.0.152.dist-info/LICENSE.txt
forensicfit-2.0.152.dist-info/METADATA
forensicfit-2.0.152.dist-info/WHEEL
forensicfit-2.0.152.dist-info/top_level.txt
forensicfit-2.0.152.dist-info/RECORD
